httpretty/__init__.py
httpretty/compat.py
httpretty/core.py
httpretty/errors.py
httpretty/http.py
httpretty/utils.py
httpretty-0.8.14.dist-info/DESCRIPTION.rst
httpretty-0.8.14.dist-info/METADATA
httpretty-0.8.14.dist-info/metadata.json
httpretty-0.8.14.dist-info/RECORD
httpretty-0.8.14.dist-info/top_level.txt
httpretty-0.8.14.dist-info/WHEEL
