Metadata-Version: 1.1
Name: httpretty
Version: 0.8.14
Summary: HTTP client mock for Python
Home-page: http://github.com/gabrielfalcao/httpretty
Author: Gabriel Falcao
Author-email: gabriel@nacaolivre.org
License: MIT
Platform: UNKNOWN
Classifier: Development Status :: 4 - Beta
Classifier: Intended Audience :: Developers
Classifier: License :: OSI Approved :: MIT License
Classifier: Programming Language :: Python :: 2
Classifier: Programming Language :: Python :: 2.6
Classifier: Programming Language :: Python :: 2.7
Classifier: Programming Language :: Python
Classifier: Topic :: Internet :: WWW/HTTP
Classifier: Topic :: Software Development :: Testing
